sd_probdist/Binomialdistribution.py
sd_probdist/Gaussiandistribution.py
sd_probdist/Generaldistribution.py
sd_probdist/__init__.py
sd_probdist-0.1.dist-info/METADATA
sd_probdist-0.1.dist-info/WHEEL
sd_probdist-0.1.dist-info/top_level.txt
sd_probdist-0.1.dist-info/RECORD
