Metadata-Version: 2.1
Name: sd-probdist
Version: 0.1
Summary: Gaussian distributions and Binomial distributions
Author: Sudip Dey
Author-email: myemail@something.com
License: MIT
